{"cameraMode":{"drawMode":0,"name":"Shaded","section":"Shading Mode"},"sceneLighting":true,"audioPlay":false,"sceneViewState":{"showFog":true,"showMaterialUpdate":false,"showSkybox":true,"showFlares":true,"showImageEffects":true,"showParticleSystems":true},"in2DMode":false,"pivot":{"x":20.351831436157228,"y":-3.459090232849121,"z":70.75050354003906},"rotation":{"x":-0.07727714627981186,"y":-0.04012968763709068,"z":0.0028213232289999725,"w":-0.9963000416755676},"size":35.678279876708987,"orthographic":false}